{
  "gitSyncId": "69774ae9b3e043360037aa21_ea15c8db-015e-49e5-8c23-486d99e545fa",
  "id": "Preenchimento de Formulário_JS_regrasEconomico.statusOptions",
  "pluginId": "js-plugin",
  "pluginType": "JS",
  "unpublishedAction": {
    "actionConfiguration": {
      "encodeParamsToggle": true,
      "jsArguments": [],
      "paginationType": "NONE",
      "timeoutInMillisecond": 10000
    },
    "collectionId": "Preenchimento de Formulário_JS_regrasEconomico",
    "confirmBeforeExecute": false,
    "datasource": {
      "isAutoGenerated": false,
      "name": "UNUSED_DATASOURCE",
      "pluginId": "js-plugin"
    },
    "dynamicBindingPathList": [
      {
        "key": "body"
      }
    ],
    "fullyQualifiedName": "JS_regrasEconomico.statusOptions",
    "name": "statusOptions",
    "pageId": "Preenchimento de Formulário",
    "runBehaviour": "MANUAL",
    "userSetOnLoad": false
  }
}