{
  "gitSyncId": "69774ae9b3e043360037aa21_fe912c89-f517-414d-82c0-8e1e1c9b7fff",
  "id": "EDIA Ranking Utilizadores_Qry_rankingSocial",
  "pluginId": "postgres-plugin",
  "pluginType": "DB",
  "unpublishedAction": {
    "actionConfiguration": {
      "body": "SELECT\n  ano,\n  id_utilizador,\n  dominio,\n  pontuacao_user AS pontuacao,\n  DENSE_RANK() OVER (\n    PARTITION BY ano, dominio\n    ORDER BY pontuacao_user DESC\n  ) AS posicao\nFROM vw_score_user_avg_dominio\nWHERE dominio = 'Social'\n\tAND ano = {{Select_year.selectedOptionValue}}\nORDER BY ano DESC, pontuacao DESC, id_utilizador ASC;",
      "encodeParamsToggle": true,
      "paginationType": "NONE",
      "pluginSpecifiedTemplates": [
        {
          "value": true
        }
      ],
      "timeoutInMillisecond": 10000
    },
    "confirmBeforeExecute": false,
    "datasource": {
      "id": "pg_alquevaustentavel",
      "isAutoGenerated": false,
      "name": "pg_alquevaustentavel",
      "pluginId": "postgres-plugin"
    },
    "dynamicBindingPathList": [
      {
        "key": "body"
      }
    ],
    "name": "Qry_rankingSocial",
    "pageId": "EDIA Ranking Utilizadores",
    "runBehaviour": "AUTOMATIC",
    "userSetOnLoad": false
  }
}